pretty_json/__init__.py
pretty_json/settings.py
pretty_json-1.2.0.dist-info/DESCRIPTION.rst
pretty_json-1.2.0.dist-info/METADATA
pretty_json-1.2.0.dist-info/RECORD
pretty_json-1.2.0.dist-info/WHEEL
pretty_json-1.2.0.dist-info/metadata.json
pretty_json-1.2.0.dist-info/top_level.txt
