Metadata-Version: 2.0
Name: pretty-json
Version: 1.2.0
Summary: make pretty json
Home-page: https://github.com/devstuff-io/pretty-json
Author: meganlkm
Author-email: devstuff.io@gmail.com
License: UNKNOWN
Keywords: pretty,json
Platform: UNKNOWN
Classifier: Intended Audience :: Developers
Classifier: License :: OSI Approved :: MIT License
Classifier: Operating System :: OS Independent
Classifier: Programming Language :: Python
Requires-Dist: Pygments
Requires-Dist: pygments-json
